README.md
setup.cfg
setup.py
autobasedoc/__init__.py
autobasedoc/autoplot.py
autobasedoc/autorpt.py
autobasedoc/fonts.py
autobasedoc/pageinfo.py
autobasedoc/pdfimage.py
autobasedoc/styledtable.py
autobasedoc/styles.py
autobasedoc/tableofcontents.py
autobasedoc/version.py
autobasedoc.egg-info/PKG-INFO
autobasedoc.egg-info/SOURCES.txt
autobasedoc.egg-info/dependency_links.txt
autobasedoc.egg-info/requires.txt
autobasedoc.egg-info/top_level.txt