Metadata-Version: 1.1
Name: autobasedoc
Version: 1.1.9
Summary: autobasedoc - convenience reportlab tool
Home-page: https://github.com/NuCOS/autobasedoc
Author: Oliver Braun, Johannes Eckstein
Author-email: johannes.eckstein@nucos.de
License: BSD
Download-URL: https://github.com/NuCOS/autobasedoc/tarball/1.1.9
Keywords: reporting
Platform: UNKNOWN
Classifier: Development Status :: 1 - Planning
Classifier: Environment :: Console
Classifier: License :: OSI Approved :: BSD License
Classifier: Natural Language :: English
Classifier: Operating System :: OS Independent
Classifier: Programming Language :: Python :: 3.5
Classifier: Programming Language :: Python :: 3.6
